icespirit/__init__.py
icespirit/main.py
icespirit-0.1.5.dist-info/LICENSE
icespirit-0.1.5.dist-info/METADATA
icespirit-0.1.5.dist-info/WHEEL
icespirit-0.1.5.dist-info/top_level.txt
icespirit-0.1.5.dist-info/RECORD
