Metadata-Version: 2.1
Name: icespirit
Version: 0.1.5
Summary: file handling
Home-page: https://github.com/iop3/icespirit
Author: iop3
Author-email: keystove@gmail.com
Project-URL: Bug Tracker, https://github.com/iop3/icespirit/issues
Classifier: Programming Language :: Python :: 3
Classifier: License :: OSI Approved :: MIT License
Classifier: Operating System :: OS Independent
Requires-Python: >=3.6
License-File: LICENSE
